{
   "package-id": "hl7.fhir.us.carin-rtpbc",
   "title": "Consumer Real-time Pharmacy Benefit Check",
   "canonical": "http://hl7.org/fhir/us/carin",
   "introduction": "Using RTPBC, a patient can learn how their medications will be covered at the pharmacy, including out of pocket costs and any coverage restrictions or requirements that might apply.",
   "list": [
      {
         "version": "current",
         "desc": "Consumer Real-time Pharmacy Benefit Check Implementation Guide CI Build",
         "path": "http://build.fhir.org/ig/HL7/carin-rtpbc",
         "status": "ci-build",
         "current": true
      },
      {
         "version": "1.0.0",
         "date": "2020-06-22",
         "desc": "Consumer Real-time Pharmacy Benefit Check Implementation Guide STU1",
         "changes": "",
         "path": "http://hl7.org/fhir/us/carin-rtpbc/STU1",
         "status": "trial-use",
         "sequence": "STU1",
         "fhirversion" : "4.0.1"
      },
      {
         "version": "0.1.0",
         "date": "2019-12-22",
         "desc": "STU1 Ballot",
         "changes": "",
         "path": "http://hl7.org/fhir/us/carin-rtpbc/2020Feb",
         "status": "ballot",
         "sequence": "STU1",
         "fhirversion" : "4.0.1"
      }
   ]
}